exoedge_ethernetip/__init__.py
exoedge_ethernetip/__version__.py
exoedge_ethernetip-0.1.1.dist-info/licenses/LICENSE
exoedge_ethernetip-0.1.1.dist-info/METADATA
exoedge_ethernetip-0.1.1.dist-info/WHEEL
exoedge_ethernetip-0.1.1.dist-info/top_level.txt
exoedge_ethernetip-0.1.1.dist-info/RECORD
