Metadata-Version: 2.4
Name: exoedge_ethernetip
Version: 0.1.1
Summary: An ExoEdge source for EtherNet/IP.
Home-page: https://github.com/exosite/lib_exoedge_ethernetIP_python
Author: Exosite LLC
Author-email: support@exosite.com
License: Apache 2.0
Keywords: murano exosite iot iiot client gateway EtherNet/IP
Classifier: Development Status :: 4 - Beta
Classifier: Programming Language :: Python :: 3
Classifier: Operating System :: POSIX :: Linux
Classifier: Topic :: System :: Operating System Kernels :: Linux
Classifier: Topic :: Software Development :: Embedded Systems
Classifier: License :: OSI Approved :: Apache Software License
Requires-Python: >=3.6
License-File: LICENSE
Requires-Dist: exoedge
Requires-Dist: ifparser
Requires-Dist: pycomm3>=0.9.0
Dynamic: author
Dynamic: author-email
Dynamic: classifier
Dynamic: description
Dynamic: home-page
Dynamic: keywords
Dynamic: license
Dynamic: license-file
Dynamic: requires-dist
Dynamic: requires-python
Dynamic: summary
